subdivx/__init__.py
subdivx/cli.py
subdivx/lib.py
subdivx_download-0.6.dist-info/METADATA
subdivx_download-0.6.dist-info/WHEEL
subdivx_download-0.6.dist-info/entry_points.txt
subdivx_download-0.6.dist-info/top_level.txt
subdivx_download-0.6.dist-info/RECORD
