Metadata-Version: 2.1
Name: subdivx-download
Version: 0.6
Summary: A command line tool to download the best matching subtitle from subdivx.com
Home-page: https://github.com/mgaitan/subdivx-download
Author: Martin Gaitán
Author-email: gaitan@gmail.com
License: GNU GENERAL PUBLIC LICENCE v3.0
Platform: UNKNOWN
Classifier: Development Status :: 4 - Beta
Classifier: Environment :: Console
Classifier: Intended Audience :: End Users/Desktop
Classifier: License :: OSI Approved :: GNU General Public License (GPL)
Classifier: Natural Language :: Spanish
Classifier: Operating System :: OS Independent
Classifier: Programming Language :: Python
Classifier: Programming Language :: Python :: 3 :: Only
Classifier: Topic :: Internet :: WWW/HTTP :: Dynamic Content
Requires-Dist: beautifulsoup4
Requires-Dist: tvnamer
Requires-Dist: guessit
